Metadata-Version: 1.0
Name: distributions-probability-winay05
Version: 0.1
Summary: Gaussian & Binomial distributions
Home-page: UNKNOWN
Author: Vinay Kumar Dahiya
Author-email: vinaykumardahiya@gmail.com
License: UNKNOWN
Platform: UNKNOWN
